tesserax/__init__.py
tesserax/base.py
tesserax/canvas.py
tesserax/core.py
tesserax/layout.py
tesserax/py.typed
tesserax-0.4.0.dist-info/METADATA
tesserax-0.4.0.dist-info/WHEEL
tesserax-0.4.0.dist-info/licenses/LICENSE
tesserax-0.4.0.dist-info/RECORD
