Metadata-Version: 2.4
Name: tesserax
Version: 0.4.0
Summary: A pure-Python library for rendering professional CS graphics.
Author-email: Alejandro Piad <apiad@apiad.net>
License-File: LICENSE
Requires-Python: >=3.12
